<?xml version="1.0" encoding="UTF-8"?>
<session sessioncode="8386891015">
<general>
<client_version>25.1.1.13</client_version>
<mode>real</mode>
<gametype>Holdem NL</gametype>
<tablename>Twister €5 SNG, 1127852751</tablename>
<tournamentcode>1127852750</tournamentcode>
<tournamentname>Twister €5 SNG</tournamentname>
<buyin>€0 + €0.35 + €4.65</buyin>
<totalbuyin>€5</totalbuyin>
<rewarddrawn>€15</rewarddrawn>
<tournamentcurrency>EUR</tournamentcurrency>
<currency>EUR</currency>
<nickname>oreiasccp</nickname>
<gamecount>13</gamecount>
<startdate>2025-06-19 05:57:49</startdate>
<place>1</place>
<win>€15</win>
<tablesize>3</tablesize>
</general>
<game gamecode="11520605424"><general><startdate>2025-06-19 05:58:05</startdate>
<round>1</round>
<failsafecounter/>
<players><player seat="10" name="oreiasccp" chips="500" dealer="0" win="80" bet="40" muck="0" rebuy="0" addon="0" merge="0" rebuychips="0" reg_code="8386891015"/>
<player seat="3" name="sarrascaeta" chips="500" dealer="1" win="0" bet="0" muck="1" rebuy="0" addon="0" merge="0" rebuychips="0" reg_code="8386890918"/>
<player seat="6" name="flushharbor73" chips="500" dealer="0" win="0" bet="40" muck="1" rebuy="0" addon="0" merge="0" rebuychips="0" reg_code="8386890932"/>
</players>
</general>
<round no="0"><action no="1" player="flushharbor73" type="1" discard="1" dealt="1" sum="10"/>
<action no="2" player="oreiasccp" type="2" sum="20"/>
</round>
<round no="1"><cards type="Pocket" player="sarrascaeta">X X</cards>
<cards type="Pocket" player="oreiasccp">S8 H5</cards>
<cards type="Pocket" player="flushharbor73">DA H7</cards>
<action no="3" player="sarrascaeta" type="0" discard="1" dealt="1" sum="0"/>
<action no="4" player="flushharbor73" type="3" discard="1" dealt="1" sum="10"/>
<action no="5" player="oreiasccp" type="4" sum="0"/>
</round>
<round no="2"><cards type="Flop">C9 D2 DQ</cards>
<action no="6" player="flushharbor73" type="4" discard="1" dealt="1" sum="0"/>
<action no="7" player="oreiasccp" type="4" sum="0"/>
</round>
<round no="3"><cards type="Turn">H8</cards>
<action no="8" player="flushharbor73" type="4" discard="1" dealt="1" sum="0"/>
<action no="9" player="oreiasccp" type="4" sum="0"/>
</round>
<round no="4"><cards type="River">H2</cards>
<action no="10" player="flushharbor73" type="4" discard="1" dealt="1" sum="0"/>
<action no="11" player="oreiasccp" type="5" sum="20"/>
<action no="12" player="flushharbor73" type="3" discard="1" dealt="1" sum="20"/>
</round>
</game>
<game gamecode="11520605531"><general><startdate>2025-06-19 05:58:48</startdate>
<round>1</round>
<failsafecounter/>
<players><player seat="3" name="sarrascaeta" chips="500" dealer="0" win="60" bet="500" muck="1" rebuy="0" addon="0" merge="0" rebuychips="0" reg_code="8386890918"/>
<player seat="6" name="flushharbor73" chips="460" dealer="1" win="0" bet="20" muck="1" rebuy="0" addon="0" merge="0" rebuychips="0" reg_code="8386890932"/>
<player seat="10" name="oreiasccp" chips="540" dealer="0" win="0" bet="20" muck="1" rebuy="0" addon="0" merge="0" rebuychips="0" reg_code="8386891015"/>
</players>
</general>
<round no="0"><action no="1" player="oreiasccp" type="1" sum="10"/>
<action no="2" player="sarrascaeta" type="2" discard="1" dealt="1" sum="20"/>
</round>
<round no="1"><cards type="Pocket" player="oreiasccp">CJ H10</cards>
<cards type="Pocket" player="flushharbor73">X X</cards>
<cards type="Pocket" player="sarrascaeta">X X</cards>
<action no="3" player="flushharbor73" type="3" discard="1" dealt="1" sum="20"/>
<action no="4" player="oreiasccp" type="3" sum="10"/>
<action no="5" player="sarrascaeta" type="23" discard="1" dealt="1" sum="500"/>
<action no="6" player="flushharbor73" type="0" discard="1" dealt="1" sum="0"/>
<action no="7" player="oreiasccp" type="0" sum="0"/>
</round>
</game>
<game gamecode="11520609803"><general><startdate>2025-06-19 05:59:07</startdate>
<round>1</round>
<failsafecounter/>
<players><player seat="6" name="flushharbor73" chips="440" dealer="0" win="20" bet="20" muck="1" rebuy="0" addon="0" merge="0" rebuychips="0" reg_code="8386890932"/>
<player seat="10" name="oreiasccp" chips="520" dealer="1" win="0" bet="0" muck="1" rebuy="0" addon="0" merge="0" rebuychips="0" reg_code="8386891015"/>
<player seat="3" name="sarrascaeta" chips="540" dealer="0" win="0" bet="10" muck="1" rebuy="0" addon="0" merge="0" rebuychips="0" reg_code="8386890918"/>
</players>
</general>
<round no="0"><action no="1" player="sarrascaeta" type="1" discard="1" dealt="1" sum="10"/>
<action no="2" player="flushharbor73" type="2" discard="1" dealt="1" sum="20"/>
</round>
<round no="1"><cards type="Pocket" player="flushharbor73">X X</cards>
<cards type="Pocket" player="oreiasccp">HK D8</cards>
<cards type="Pocket" player="sarrascaeta">X X</cards>
<action no="3" player="oreiasccp" type="0" sum="0"/>
<action no="4" player="sarrascaeta" type="0" discard="1" dealt="1" sum="0"/>
</round>
</game>
<game gamecode="11520609841"><general><startdate>2025-06-19 05:59:22</startdate>
<round>1</round>
<failsafecounter/>
<players><player seat="10" name="oreiasccp" chips="520" dealer="0" win="0" bet="120" muck="1" rebuy="0" addon="0" merge="0" rebuychips="0" reg_code="8386891015"/>
<player seat="3" name="sarrascaeta" chips="530" dealer="1" win="0" bet="0" muck="1" rebuy="0" addon="0" merge="0" rebuychips="0" reg_code="8386890918"/>
<player seat="6" name="flushharbor73" chips="450" dealer="0" win="240" bet="260" muck="1" rebuy="0" addon="0" merge="0" rebuychips="0" reg_code="8386890932"/>
</players>
</general>
<round no="0"><action no="1" player="flushharbor73" type="1" discard="1" dealt="1" sum="10"/>
<action no="2" player="oreiasccp" type="2" sum="20"/>
</round>
<round no="1"><cards type="Pocket" player="oreiasccp">S6 H7</cards>
<cards type="Pocket" player="flushharbor73">X X</cards>
<cards type="Pocket" player="sarrascaeta">X X</cards>
<action no="3" player="sarrascaeta" type="0" discard="1" dealt="1" sum="0"/>
<action no="4" player="flushharbor73" type="23" discard="1" dealt="1" sum="40"/>
<action no="5" player="oreiasccp" type="3" sum="20"/>
</round>
<round no="2"><cards type="Flop">D9 CQ C8</cards>
<action no="6" player="flushharbor73" type="5" discard="1" dealt="1" sum="80"/>
<action no="7" player="oreiasccp" type="3" sum="80"/>
</round>
<round no="3"><cards type="Turn">SJ</cards>
<action no="8" player="flushharbor73" type="5" discard="1" dealt="1" sum="140"/>
<action no="9" player="oreiasccp" type="0" sum="0"/>
</round>
</game>
<game gamecode="11520609910"><general><startdate>2025-06-19 05:59:51</startdate>
<round>1</round>
<failsafecounter/>
<players><player seat="3" name="sarrascaeta" chips="530" dealer="0" win="0" bet="60" muck="1" rebuy="0" addon="0" merge="0" rebuychips="0" reg_code="8386890918"/>
<player seat="6" name="flushharbor73" chips="570" dealer="1" win="0" bet="0" muck="1" rebuy="0" addon="0" merge="0" rebuychips="0" reg_code="8386890932"/>
<player seat="10" name="oreiasccp" chips="400" dealer="0" win="120" bet="148" muck="1" rebuy="0" addon="0" merge="0" rebuychips="0" reg_code="8386891015"/>
</players>
</general>
<round no="0"><action no="1" player="oreiasccp" type="1" sum="10"/>
<action no="2" player="sarrascaeta" type="2" discard="1" dealt="1" sum="20"/>
</round>
<round no="1"><cards type="Pocket" player="oreiasccp">C9 S7</cards>
<cards type="Pocket" player="flushharbor73">X X</cards>
<cards type="Pocket" player="sarrascaeta">X X</cards>
<action no="3" player="flushharbor73" type="0" discard="1" dealt="1" sum="0"/>
<action no="4" player="oreiasccp" type="23" sum="40"/>
<action no="5" player="sarrascaeta" type="3" discard="1" dealt="1" sum="20"/>
</round>
<round no="2"><cards type="Flop">HK SJ C5</cards>
<action no="6" player="oreiasccp" type="5" sum="20"/>
<action no="7" player="sarrascaeta" type="3" discard="1" dealt="1" sum="20"/>
</round>
<round no="3"><cards type="Turn">H8</cards>
<action no="8" player="oreiasccp" type="5" sum="88"/>
<action no="9" player="sarrascaeta" type="0" discard="1" dealt="1" sum="0"/>
</round>
</game>
<game gamecode="11520609996"><general><startdate>2025-06-19 06:00:20</startdate>
<round>1</round>
<failsafecounter/>
<players><player seat="6" name="flushharbor73" chips="570" dealer="0" win="75" bet="125" muck="1" rebuy="0" addon="0" merge="0" rebuychips="0" reg_code="8386890932"/>
<player seat="10" name="oreiasccp" chips="460" dealer="1" win="0" bet="5" muck="1" rebuy="0" addon="0" merge="0" rebuychips="0" reg_code="8386891015"/>
<player seat="3" name="sarrascaeta" chips="470" dealer="0" win="0" bet="35" muck="1" rebuy="0" addon="0" merge="0" rebuychips="0" reg_code="8386890918"/>
</players>
</general>
<round no="0"><action no="1" player="sarrascaeta" type="15" discard="1" dealt="1" sum="5"/>
<action no="2" player="flushharbor73" type="15" discard="1" dealt="1" sum="5"/>
<action no="3" player="oreiasccp" type="15" sum="5"/>
<action no="4" player="sarrascaeta" type="1" discard="1" dealt="1" sum="15"/>
<action no="5" player="flushharbor73" type="2" discard="1" dealt="1" sum="30"/>
</round>
<round no="1"><cards type="Pocket" player="oreiasccp">S9 C6</cards>
<cards type="Pocket" player="sarrascaeta">X X</cards>
<cards type="Pocket" player="flushharbor73">X X</cards>
<action no="6" player="oreiasccp" type="0" sum="0"/>
<action no="7" player="sarrascaeta" type="3" discard="1" dealt="1" sum="15"/>
<action no="8" player="flushharbor73" type="4" discard="1" dealt="1" sum="0"/>
</round>
<round no="2"><cards type="Flop">D8 D6 D10</cards>
<action no="9" player="sarrascaeta" type="4" discard="1" dealt="1" sum="0"/>
<action no="10" player="flushharbor73" type="5" discard="1" dealt="1" sum="90"/>
<action no="11" player="sarrascaeta" type="0" discard="1" dealt="1" sum="0"/>
</round>
</game>
<game gamecode="11520610073"><general><startdate>2025-06-19 06:00:53</startdate>
<round>1</round>
<failsafecounter/>
<players><player seat="10" name="oreiasccp" chips="455" dealer="0" win="0" bet="65" muck="1" rebuy="0" addon="0" merge="0" rebuychips="0" reg_code="8386891015"/>
<player seat="3" name="sarrascaeta" chips="435" dealer="1" win="0" bet="5" muck="1" rebuy="0" addon="0" merge="0" rebuychips="0" reg_code="8386890918"/>
<player seat="6" name="flushharbor73" chips="610" dealer="0" win="135" bet="65" muck="0" rebuy="0" addon="0" merge="0" rebuychips="0" reg_code="8386890932"/>
</players>
</general>
<round no="0"><action no="1" player="flushharbor73" type="15" discard="1" dealt="1" sum="5"/>
<action no="2" player="oreiasccp" type="15" sum="5"/>
<action no="3" player="sarrascaeta" type="15" discard="1" dealt="1" sum="5"/>
<action no="4" player="flushharbor73" type="1" discard="1" dealt="1" sum="15"/>
<action no="5" player="oreiasccp" type="2" sum="30"/>
</round>
<round no="1"><cards type="Pocket" player="sarrascaeta">X X</cards>
<cards type="Pocket" player="flushharbor73">S10 HA</cards>
<cards type="Pocket" player="oreiasccp">CQ S5</cards>
<action no="6" player="sarrascaeta" type="0" discard="1" dealt="1" sum="0"/>
<action no="7" player="flushharbor73" type="23" discard="1" dealt="1" sum="60"/>
<action no="8" player="oreiasccp" type="3" sum="30"/>
</round>
<round no="2"><cards type="Flop">C8 S4 H7</cards>
<action no="9" player="flushharbor73" type="4" discard="1" dealt="1" sum="0"/>
<action no="10" player="oreiasccp" type="4" sum="0"/>
</round>
<round no="3"><cards type="Turn">SJ</cards>
<action no="11" player="flushharbor73" type="4" discard="1" dealt="1" sum="0"/>
<action no="12" player="oreiasccp" type="4" sum="0"/>
</round>
<round no="4"><cards type="River">CK</cards>
<action no="13" player="flushharbor73" type="4" discard="1" dealt="1" sum="0"/>
<action no="14" player="oreiasccp" type="4" sum="0"/>
</round>
</game>
<game gamecode="11520610170"><general><startdate>2025-06-19 06:01:36</startdate>
<round>1</round>
<failsafecounter/>
<players><player seat="3" name="sarrascaeta" chips="430" dealer="0" win="0" bet="390" muck="1" rebuy="0" addon="0" merge="0" rebuychips="0" reg_code="8386890918"/>
<player seat="6" name="flushharbor73" chips="680" dealer="1" win="0" bet="5" muck="1" rebuy="0" addon="0" merge="0" rebuychips="0" reg_code="8386890932"/>
<player seat="10" name="oreiasccp" chips="390" dealer="0" win="785" bet="390" muck="0" rebuy="0" addon="0" merge="0" rebuychips="0" reg_code="8386891015"/>
</players>
</general>
<round no="0"><action no="1" player="oreiasccp" type="15" sum="5"/>
<action no="2" player="sarrascaeta" type="15" discard="1" dealt="1" sum="5"/>
<action no="3" player="flushharbor73" type="15" discard="1" dealt="1" sum="5"/>
<action no="4" player="oreiasccp" type="1" sum="15"/>
<action no="5" player="sarrascaeta" type="2" discard="1" dealt="1" sum="30"/>
</round>
<round no="1"><cards type="Pocket" player="oreiasccp">H6 H5</cards>
<cards type="Pocket" player="flushharbor73">X X</cards>
<cards type="Pocket" player="sarrascaeta">SK D10</cards>
<action no="6" player="flushharbor73" type="0" discard="1" dealt="1" sum="0"/>
<action no="7" player="oreiasccp" type="23" sum="385"/>
<action no="8" player="sarrascaeta" type="3" discard="1" dealt="1" sum="355"/>
</round>
<round no="2"><cards type="Flop">H4 S7 HJ</cards>
</round>
<round no="3"><cards type="Turn">C6</cards>
</round>
<round no="4"><cards type="River">D3</cards>
</round>
</game>
<game gamecode="11520610251"><general><startdate>2025-06-19 06:02:09</startdate>
<round>1</round>
<failsafecounter/>
<players><player seat="6" name="flushharbor73" chips="675" dealer="0" win="0" bet="45" muck="1" rebuy="0" addon="0" merge="0" rebuychips="0" reg_code="8386890932"/>
<player seat="10" name="oreiasccp" chips="785" dealer="1" win="0" bet="5" muck="1" rebuy="0" addon="0" merge="0" rebuychips="0" reg_code="8386891015"/>
<player seat="3" name="sarrascaeta" chips="40" dealer="0" win="85" bet="40" muck="0" rebuy="0" addon="0" merge="0" rebuychips="0" reg_code="8386890918"/>
</players>
</general>
<round no="0"><action no="1" player="sarrascaeta" type="15" discard="1" dealt="1" sum="5"/>
<action no="2" player="flushharbor73" type="15" discard="1" dealt="1" sum="5"/>
<action no="3" player="oreiasccp" type="15" sum="5"/>
<action no="4" player="sarrascaeta" type="1" discard="1" dealt="1" sum="20"/>
<action no="5" player="flushharbor73" type="2" discard="1" dealt="1" sum="40"/>
</round>
<round no="1"><cards type="Pocket" player="flushharbor73">D4 C4</cards>
<cards type="Pocket" player="oreiasccp">HK H3</cards>
<cards type="Pocket" player="sarrascaeta">S2 H9</cards>
<action no="6" player="oreiasccp" type="0" sum="0"/>
<action no="7" player="sarrascaeta" type="7" discard="1" dealt="1" sum="15"/>
</round>
<round no="2"><cards type="Flop">CK DJ H2</cards>
</round>
<round no="3"><cards type="Turn">C6</cards>
</round>
<round no="4"><cards type="River">D9</cards>
</round>
</game>
<game gamecode="11520610302"><general><startdate>2025-06-19 06:02:34</startdate>
<round>1</round>
<failsafecounter/>
<players><player seat="10" name="oreiasccp" chips="780" dealer="0" win="0" bet="85" muck="1" rebuy="0" addon="0" merge="0" rebuychips="0" reg_code="8386891015"/>
<player seat="3" name="sarrascaeta" chips="85" dealer="1" win="195" bet="85" muck="0" rebuy="0" addon="0" merge="0" rebuychips="0" reg_code="8386890918"/>
<player seat="6" name="flushharbor73" chips="635" dealer="0" win="0" bet="25" muck="1" rebuy="0" addon="0" merge="0" rebuychips="0" reg_code="8386890932"/>
</players>
</general>
<round no="0"><action no="1" player="flushharbor73" type="15" discard="1" dealt="1" sum="5"/>
<action no="2" player="oreiasccp" type="15" sum="5"/>
<action no="3" player="sarrascaeta" type="15" discard="1" dealt="1" sum="5"/>
<action no="4" player="flushharbor73" type="1" discard="1" dealt="1" sum="20"/>
<action no="5" player="oreiasccp" type="2" sum="40"/>
</round>
<round no="1"><cards type="Pocket" player="sarrascaeta">SK HA</cards>
<cards type="Pocket" player="oreiasccp">CA C9</cards>
<cards type="Pocket" player="flushharbor73">X X</cards>
<action no="6" player="sarrascaeta" type="7" discard="1" dealt="1" sum="80"/>
<action no="7" player="flushharbor73" type="0" discard="1" dealt="1" sum="0"/>
<action no="8" player="oreiasccp" type="3" sum="40"/>
</round>
<round no="2"><cards type="Flop">CK HJ C5</cards>
</round>
<round no="3"><cards type="Turn">SJ</cards>
</round>
<round no="4"><cards type="River">DA</cards>
</round>
</game>
<game gamecode="11520610359"><general><startdate>2025-06-19 06:02:57</startdate>
<round>1</round>
<failsafecounter/>
<players><player seat="3" name="sarrascaeta" chips="195" dealer="0" win="0" bet="195" muck="0" rebuy="0" addon="0" merge="0" rebuychips="0" reg_code="8386890918"/>
<player seat="6" name="flushharbor73" chips="610" dealer="1" win="415" bet="195" muck="0" rebuy="0" addon="0" merge="0" rebuychips="0" reg_code="8386890932"/>
<player seat="10" name="oreiasccp" chips="695" dealer="0" win="0" bet="25" muck="1" rebuy="0" addon="0" merge="0" rebuychips="0" reg_code="8386891015"/>
</players>
</general>
<round no="0"><action no="1" player="oreiasccp" type="15" sum="5"/>
<action no="2" player="sarrascaeta" type="15" discard="1" dealt="1" sum="5"/>
<action no="3" player="flushharbor73" type="15" discard="1" dealt="1" sum="5"/>
<action no="4" player="oreiasccp" type="1" sum="20"/>
<action no="5" player="sarrascaeta" type="2" discard="1" dealt="1" sum="40"/>
</round>
<round no="1"><cards type="Pocket" player="flushharbor73">SA S8</cards>
<cards type="Pocket" player="sarrascaeta">H7 SK</cards>
<cards type="Pocket" player="oreiasccp">H10 D2</cards>
<action no="6" player="flushharbor73" type="23" discard="1" dealt="1" sum="80"/>
<action no="7" player="oreiasccp" type="0" sum="0"/>
<action no="8" player="sarrascaeta" type="23" discard="1" dealt="1" sum="190"/>
<action no="9" player="flushharbor73" type="3" discard="1" dealt="1" sum="110"/>
</round>
<round no="2"><cards type="Flop">CK C8 H8</cards>
</round>
<round no="3"><cards type="Turn">SJ</cards>
</round>
<round no="4"><cards type="River">DQ</cards>
</round>
</game>
<game gamecode="11520610419"><general><startdate>2025-06-19 06:03:22</startdate>
<round>1</round>
<failsafecounter/>
<players><player seat="6" name="flushharbor73" chips="830" dealer="0" win="0" bet="670" muck="1" rebuy="0" addon="0" merge="0" rebuychips="0" reg_code="8386890932"/>
<player seat="10" name="oreiasccp" chips="670" dealer="1" win="1,340" bet="670" muck="0" rebuy="0" addon="0" merge="0" rebuychips="0" reg_code="8386891015"/>
</players>
</general>
<round no="0"><action no="1" player="oreiasccp" type="15" sum="5"/>
<action no="2" player="flushharbor73" type="15" discard="1" dealt="1" sum="5"/>
<action no="3" player="oreiasccp" type="1" sum="20"/>
<action no="4" player="flushharbor73" type="2" discard="1" dealt="1" sum="40"/>
</round>
<round no="1"><cards type="Pocket" player="flushharbor73">H5 CA</cards>
<cards type="Pocket" player="oreiasccp">HA C7</cards>
<action no="5" player="oreiasccp" type="23" sum="665"/>
<action no="6" player="flushharbor73" type="3" discard="1" dealt="1" sum="625"/>
</round>
<round no="2"><cards type="Flop">S7 CK D10</cards>
</round>
<round no="3"><cards type="Turn">CJ</cards>
</round>
<round no="4"><cards type="River">D8</cards>
</round>
</game>
<game gamecode="11520610462"><general><startdate>2025-06-19 06:03:41</startdate>
<round>1</round>
<failsafecounter/>
<players><player seat="10" name="oreiasccp" chips="1,340" dealer="0" win="320" bet="160" muck="0" rebuy="0" addon="0" merge="0" rebuychips="0" reg_code="8386891015"/>
<player seat="6" name="flushharbor73" chips="160" dealer="1" win="0" bet="160" muck="1" rebuy="0" addon="0" merge="0" rebuychips="0" reg_code="8386890932"/>
</players>
</general>
<round no="0"><action no="1" player="flushharbor73" type="15" discard="1" dealt="1" sum="5"/>
<action no="2" player="oreiasccp" type="15" sum="5"/>
<action no="3" player="flushharbor73" type="1" discard="1" dealt="1" sum="20"/>
<action no="4" player="oreiasccp" type="2" sum="40"/>
</round>
<round no="1"><cards type="Pocket" player="oreiasccp">S3 HK</cards>
<cards type="Pocket" player="flushharbor73">C4 S5</cards>
<action no="5" player="flushharbor73" type="23" discard="1" dealt="1" sum="80"/>
<action no="6" player="oreiasccp" type="23" sum="155"/>
<action no="7" player="flushharbor73" type="7" discard="1" dealt="1" sum="75"/>
</round>
<round no="2"><cards type="Flop">C8 D7 D5</cards>
</round>
<round no="3"><cards type="Turn">C2</cards>
</round>
<round no="4"><cards type="River">SK</cards>
</round>
</game>
</session>
