<?xml version="1.0" encoding="UTF-8"?>
<session sessioncode="8394365221">
<general>
<client_version>25.1.1.13</client_version>
<mode>real</mode>
<gametype>Holdem NL</gametype>
<tablename>Twister €5 SNG, 1128866525</tablename>
<tournamentcode>1128866524</tournamentcode>
<tournamentname>Twister €5 SNG</tournamentname>
<buyin>€0 + €0.35 + €4.65</buyin>
<totalbuyin>€5</totalbuyin>
<rewarddrawn>€25</rewarddrawn>
<tournamentcurrency>EUR</tournamentcurrency>
<currency>EUR</currency>
<nickname>oreiasccp</nickname>
<gamecount>19</gamecount>
<startdate>2025-06-29 14:35:02</startdate>
<place>1</place>
<win>€25</win>
<tablesize>3</tablesize>
</general>
<game gamecode="11540922039"><general><startdate>2025-06-29 14:35:17</startdate>
<round>1</round>
<failsafecounter/>
<players><player seat="6" name="Elbarto212" chips="500" dealer="0" win="0" bet="20" muck="1" rebuy="0" addon="0" merge="0" rebuychips="0" reg_code="8394365250"/>
<player seat="10" name="Freya761" chips="500" dealer="1" win="50" bet="500" muck="1" rebuy="0" addon="0" merge="0" rebuychips="0" reg_code="8394365259"/>
<player seat="3" name="oreiasccp" chips="500" dealer="0" win="0" bet="10" muck="1" rebuy="0" addon="0" merge="0" rebuychips="0" reg_code="8394365221"/>
</players>
</general>
<round no="0"><action no="1" player="oreiasccp" type="1" sum="10"/>
<action no="2" player="Elbarto212" type="2" discard="1" dealt="1" sum="20"/>
</round>
<round no="1"><cards type="Pocket" player="Elbarto212">X X</cards>
<cards type="Pocket" player="Freya761">X X</cards>
<cards type="Pocket" player="oreiasccp">HJ D10</cards>
<action no="3" player="Freya761" type="23" discard="1" dealt="1" sum="500"/>
<action no="4" player="oreiasccp" type="0" sum="0"/>
<action no="5" player="Elbarto212" type="0" discard="1" dealt="1" sum="0"/>
</round>
</game>
<game gamecode="11540922081"><general><startdate>2025-06-29 14:35:27</startdate>
<round>1</round>
<failsafecounter/>
<players><player seat="10" name="Freya761" chips="530" dealer="0" win="0" bet="20" muck="1" rebuy="0" addon="0" merge="0" rebuychips="0" reg_code="8394365259"/>
<player seat="3" name="oreiasccp" chips="490" dealer="1" win="0" bet="0" muck="1" rebuy="0" addon="0" merge="0" rebuychips="0" reg_code="8394365221"/>
<player seat="6" name="Elbarto212" chips="480" dealer="0" win="40" bet="50" muck="1" rebuy="0" addon="0" merge="0" rebuychips="0" reg_code="8394365250"/>
</players>
</general>
<round no="0"><action no="1" player="Elbarto212" type="1" discard="1" dealt="1" sum="10"/>
<action no="2" player="Freya761" type="2" discard="1" dealt="1" sum="20"/>
</round>
<round no="1"><cards type="Pocket" player="oreiasccp">C7 D3</cards>
<cards type="Pocket" player="Freya761">X X</cards>
<cards type="Pocket" player="Elbarto212">X X</cards>
<action no="3" player="oreiasccp" type="0" sum="0"/>
<action no="4" player="Elbarto212" type="3" discard="1" dealt="1" sum="10"/>
<action no="5" player="Freya761" type="4" discard="1" dealt="1" sum="0"/>
</round>
<round no="2"><cards type="Flop">H4 HJ HQ</cards>
<action no="6" player="Elbarto212" type="4" discard="1" dealt="1" sum="0"/>
<action no="7" player="Freya761" type="4" discard="1" dealt="1" sum="0"/>
</round>
<round no="3"><cards type="Turn">DQ</cards>
<action no="8" player="Elbarto212" type="5" discard="1" dealt="1" sum="30"/>
<action no="9" player="Freya761" type="0" discard="1" dealt="1" sum="0"/>
</round>
</game>
<game gamecode="11540922154"><general><startdate>2025-06-29 14:35:47</startdate>
<round>1</round>
<failsafecounter/>
<players><player seat="3" name="oreiasccp" chips="490" dealer="0" win="180" bet="130" muck="1" rebuy="0" addon="0" merge="0" rebuychips="0" reg_code="8394365221"/>
<player seat="6" name="Elbarto212" chips="500" dealer="1" win="0" bet="85" muck="1" rebuy="0" addon="0" merge="0" rebuychips="0" reg_code="8394365250"/>
<player seat="10" name="Freya761" chips="510" dealer="0" win="0" bet="10" muck="1" rebuy="0" addon="0" merge="0" rebuychips="0" reg_code="8394365259"/>
</players>
</general>
<round no="0"><action no="1" player="Freya761" type="1" discard="1" dealt="1" sum="10"/>
<action no="2" player="oreiasccp" type="2" sum="20"/>
</round>
<round no="1"><cards type="Pocket" player="oreiasccp">H7 DQ</cards>
<cards type="Pocket" player="Freya761">X X</cards>
<cards type="Pocket" player="Elbarto212">X X</cards>
<action no="3" player="Elbarto212" type="23" discard="1" dealt="1" sum="40"/>
<action no="4" player="Freya761" type="0" discard="1" dealt="1" sum="0"/>
<action no="5" player="oreiasccp" type="3" sum="20"/>
</round>
<round no="2"><cards type="Flop">C6 H8 SQ</cards>
<action no="6" player="oreiasccp" type="4" sum="0"/>
<action no="7" player="Elbarto212" type="5" discard="1" dealt="1" sum="45"/>
<action no="8" player="oreiasccp" type="3" sum="45"/>
</round>
<round no="3"><cards type="Turn">D5</cards>
<action no="9" player="oreiasccp" type="4" sum="0"/>
<action no="10" player="Elbarto212" type="4" discard="1" dealt="1" sum="0"/>
</round>
<round no="4"><cards type="River">CQ</cards>
<action no="11" player="oreiasccp" type="5" sum="45"/>
<action no="12" player="Elbarto212" type="0" discard="1" dealt="1" sum="0"/>
</round>
</game>
<game gamecode="11540922267"><general><startdate>2025-06-29 14:36:15</startdate>
<round>1</round>
<failsafecounter/>
<players><player seat="6" name="Elbarto212" chips="415" dealer="0" win="0" bet="20" muck="1" rebuy="0" addon="0" merge="0" rebuychips="0" reg_code="8394365250"/>
<player seat="10" name="Freya761" chips="500" dealer="1" win="0" bet="40" muck="1" rebuy="0" addon="0" merge="0" rebuychips="0" reg_code="8394365259"/>
<player seat="3" name="oreiasccp" chips="585" dealer="0" win="100" bet="500" muck="1" rebuy="0" addon="0" merge="0" rebuychips="0" reg_code="8394365221"/>
</players>
</general>
<round no="0"><action no="1" player="oreiasccp" type="1" sum="10"/>
<action no="2" player="Elbarto212" type="2" discard="1" dealt="1" sum="20"/>
</round>
<round no="1"><cards type="Pocket" player="oreiasccp">SK DQ</cards>
<cards type="Pocket" player="Freya761">X X</cards>
<cards type="Pocket" player="Elbarto212">X X</cards>
<action no="3" player="Freya761" type="23" discard="1" dealt="1" sum="40"/>
<action no="4" player="oreiasccp" type="23" sum="500"/>
<action no="5" player="Elbarto212" type="0" discard="1" dealt="1" sum="0"/>
<action no="6" player="Freya761" type="0" discard="1" dealt="1" sum="0"/>
</round>
</game>
<game gamecode="11540922332"><general><startdate>2025-06-29 14:36:29</startdate>
<round>1</round>
<failsafecounter/>
<players><player seat="10" name="Freya761" chips="460" dealer="0" win="40" bet="460" muck="1" rebuy="0" addon="0" merge="0" rebuychips="0" reg_code="8394365259"/>
<player seat="3" name="oreiasccp" chips="645" dealer="1" win="0" bet="0" muck="1" rebuy="0" addon="0" merge="0" rebuychips="0" reg_code="8394365221"/>
<player seat="6" name="Elbarto212" chips="395" dealer="0" win="0" bet="20" muck="1" rebuy="0" addon="0" merge="0" rebuychips="0" reg_code="8394365250"/>
</players>
</general>
<round no="0"><action no="1" player="Elbarto212" type="1" discard="1" dealt="1" sum="10"/>
<action no="2" player="Freya761" type="2" discard="1" dealt="1" sum="20"/>
</round>
<round no="1"><cards type="Pocket" player="oreiasccp">H5 CJ</cards>
<cards type="Pocket" player="Freya761">X X</cards>
<cards type="Pocket" player="Elbarto212">X X</cards>
<action no="3" player="oreiasccp" type="0" sum="0"/>
<action no="4" player="Elbarto212" type="3" discard="1" dealt="1" sum="10"/>
<action no="5" player="Freya761" type="23" discard="1" dealt="1" sum="460"/>
<action no="6" player="Elbarto212" type="0" discard="1" dealt="1" sum="0"/>
</round>
</game>
<game gamecode="11540922385"><general><startdate>2025-06-29 14:36:42</startdate>
<round>1</round>
<failsafecounter/>
<players><player seat="3" name="oreiasccp" chips="645" dealer="0" win="0" bet="60" muck="1" rebuy="0" addon="0" merge="0" rebuychips="0" reg_code="8394365221"/>
<player seat="6" name="Elbarto212" chips="375" dealer="1" win="0" bet="0" muck="1" rebuy="0" addon="0" merge="0" rebuychips="0" reg_code="8394365250"/>
<player seat="10" name="Freya761" chips="480" dealer="0" win="120" bet="60" muck="0" rebuy="0" addon="0" merge="0" rebuychips="0" reg_code="8394365259"/>
</players>
</general>
<round no="0"><action no="1" player="Freya761" type="1" discard="1" dealt="1" sum="10"/>
<action no="2" player="oreiasccp" type="2" sum="20"/>
</round>
<round no="1"><cards type="Pocket" player="Elbarto212">X X</cards>
<cards type="Pocket" player="oreiasccp">S7 CA</cards>
<cards type="Pocket" player="Freya761">HJ S8</cards>
<action no="3" player="Elbarto212" type="0" discard="1" dealt="1" sum="0"/>
<action no="4" player="Freya761" type="23" discard="1" dealt="1" sum="40"/>
<action no="5" player="oreiasccp" type="3" sum="20"/>
</round>
<round no="2"><cards type="Flop">D10 H7 CQ</cards>
<action no="6" player="Freya761" type="5" discard="1" dealt="1" sum="20"/>
<action no="7" player="oreiasccp" type="3" sum="20"/>
</round>
<round no="3"><cards type="Turn">D8</cards>
<action no="8" player="Freya761" type="4" discard="1" dealt="1" sum="0"/>
<action no="9" player="oreiasccp" type="4" sum="0"/>
</round>
<round no="4"><cards type="River">D6</cards>
<action no="10" player="Freya761" type="4" discard="1" dealt="1" sum="0"/>
<action no="11" player="oreiasccp" type="4" sum="0"/>
</round>
</game>
<game gamecode="11540922532"><general><startdate>2025-06-29 14:37:16</startdate>
<round>1</round>
<failsafecounter/>
<players><player seat="6" name="Elbarto212" chips="375" dealer="0" win="20" bet="20" muck="1" rebuy="0" addon="0" merge="0" rebuychips="0" reg_code="8394365250"/>
<player seat="10" name="Freya761" chips="540" dealer="1" win="0" bet="0" muck="1" rebuy="0" addon="0" merge="0" rebuychips="0" reg_code="8394365259"/>
<player seat="3" name="oreiasccp" chips="585" dealer="0" win="0" bet="10" muck="1" rebuy="0" addon="0" merge="0" rebuychips="0" reg_code="8394365221"/>
</players>
</general>
<round no="0"><action no="1" player="oreiasccp" type="1" sum="10"/>
<action no="2" player="Elbarto212" type="2" discard="1" dealt="1" sum="20"/>
</round>
<round no="1"><cards type="Pocket" player="oreiasccp">S3 H5</cards>
<cards type="Pocket" player="Freya761">X X</cards>
<cards type="Pocket" player="Elbarto212">X X</cards>
<action no="3" player="Freya761" type="0" discard="1" dealt="1" sum="0"/>
<action no="4" player="oreiasccp" type="0" sum="0"/>
</round>
</game>
<game gamecode="11540922569"><general><startdate>2025-06-29 14:37:25</startdate>
<round>1</round>
<failsafecounter/>
<players><player seat="10" name="Freya761" chips="540" dealer="0" win="0" bet="35" muck="1" rebuy="0" addon="0" merge="0" rebuychips="0" reg_code="8394365259"/>
<player seat="3" name="oreiasccp" chips="575" dealer="1" win="0" bet="5" muck="1" rebuy="0" addon="0" merge="0" rebuychips="0" reg_code="8394365221"/>
<player seat="6" name="Elbarto212" chips="385" dealer="0" win="75" bet="65" muck="1" rebuy="0" addon="0" merge="0" rebuychips="0" reg_code="8394365250"/>
</players>
</general>
<round no="0"><action no="1" player="Elbarto212" type="15" discard="1" dealt="1" sum="5"/>
<action no="2" player="Freya761" type="15" discard="1" dealt="1" sum="5"/>
<action no="3" player="oreiasccp" type="15" sum="5"/>
<action no="4" player="Elbarto212" type="1" discard="1" dealt="1" sum="15"/>
<action no="5" player="Freya761" type="2" discard="1" dealt="1" sum="30"/>
</round>
<round no="1"><cards type="Pocket" player="Freya761">X X</cards>
<cards type="Pocket" player="oreiasccp">S8 H2</cards>
<cards type="Pocket" player="Elbarto212">X X</cards>
<action no="6" player="oreiasccp" type="0" sum="0"/>
<action no="7" player="Elbarto212" type="3" discard="1" dealt="1" sum="15"/>
<action no="8" player="Freya761" type="4" discard="1" dealt="1" sum="0"/>
</round>
<round no="2"><cards type="Flop">DK HA HK</cards>
<action no="9" player="Elbarto212" type="5" discard="1" dealt="1" sum="30"/>
<action no="10" player="Freya761" type="0" discard="1" dealt="1" sum="0"/>
</round>
</game>
<game gamecode="11540922663"><general><startdate>2025-06-29 14:37:46</startdate>
<round>1</round>
<failsafecounter/>
<players><player seat="3" name="oreiasccp" chips="570" dealer="0" win="250" bet="240" muck="1" rebuy="0" addon="0" merge="0" rebuychips="0" reg_code="8394365221"/>
<player seat="6" name="Elbarto212" chips="425" dealer="1" win="0" bet="115" muck="1" rebuy="0" addon="0" merge="0" rebuychips="0" reg_code="8394365250"/>
<player seat="10" name="Freya761" chips="505" dealer="0" win="0" bet="20" muck="1" rebuy="0" addon="0" merge="0" rebuychips="0" reg_code="8394365259"/>
</players>
</general>
<round no="0"><action no="1" player="Freya761" type="15" discard="1" dealt="1" sum="5"/>
<action no="2" player="oreiasccp" type="15" sum="5"/>
<action no="3" player="Elbarto212" type="15" discard="1" dealt="1" sum="5"/>
<action no="4" player="Freya761" type="1" discard="1" dealt="1" sum="15"/>
<action no="5" player="oreiasccp" type="2" sum="30"/>
</round>
<round no="1"><cards type="Pocket" player="Elbarto212">X X</cards>
<cards type="Pocket" player="Freya761">X X</cards>
<cards type="Pocket" player="oreiasccp">S10 D9</cards>
<action no="6" player="Elbarto212" type="23" discard="1" dealt="1" sum="60"/>
<action no="7" player="Freya761" type="0" discard="1" dealt="1" sum="0"/>
<action no="8" player="oreiasccp" type="3" sum="30"/>
</round>
<round no="2"><cards type="Flop">SA S2 SJ</cards>
<action no="9" player="oreiasccp" type="4" sum="0"/>
<action no="10" player="Elbarto212" type="5" discard="1" dealt="1" sum="50"/>
<action no="11" player="oreiasccp" type="3" sum="50"/>
</round>
<round no="3"><cards type="Turn">SQ</cards>
<action no="12" player="oreiasccp" type="4" sum="0"/>
<action no="13" player="Elbarto212" type="4" discard="1" dealt="1" sum="0"/>
</round>
<round no="4"><cards type="River">DQ</cards>
<action no="14" player="oreiasccp" type="5" sum="125"/>
<action no="15" player="Elbarto212" type="0" discard="1" dealt="1" sum="0"/>
</round>
</game>
<game gamecode="11540922843"><general><startdate>2025-06-29 14:38:30</startdate>
<round>1</round>
<failsafecounter/>
<players><player seat="6" name="Elbarto212" chips="310" dealer="0" win="0" bet="35" muck="1" rebuy="0" addon="0" merge="0" rebuychips="0" reg_code="8394365250"/>
<player seat="10" name="Freya761" chips="485" dealer="1" win="90" bet="65" muck="1" rebuy="0" addon="0" merge="0" rebuychips="0" reg_code="8394365259"/>
<player seat="3" name="oreiasccp" chips="705" dealer="0" win="0" bet="20" muck="1" rebuy="0" addon="0" merge="0" rebuychips="0" reg_code="8394365221"/>
</players>
</general>
<round no="0"><action no="1" player="oreiasccp" type="15" sum="5"/>
<action no="2" player="Elbarto212" type="15" discard="1" dealt="1" sum="5"/>
<action no="3" player="Freya761" type="15" discard="1" dealt="1" sum="5"/>
<action no="4" player="oreiasccp" type="1" sum="15"/>
<action no="5" player="Elbarto212" type="2" discard="1" dealt="1" sum="30"/>
</round>
<round no="1"><cards type="Pocket" player="Freya761">X X</cards>
<cards type="Pocket" player="Elbarto212">X X</cards>
<cards type="Pocket" player="oreiasccp">H6 D3</cards>
<action no="6" player="Freya761" type="23" discard="1" dealt="1" sum="60"/>
<action no="7" player="oreiasccp" type="0" sum="0"/>
<action no="8" player="Elbarto212" type="0" discard="1" dealt="1" sum="0"/>
</round>
</game>
<game gamecode="11540930982"><general><startdate>2025-06-29 14:38:39</startdate>
<round>1</round>
<failsafecounter/>
<players><player seat="10" name="Freya761" chips="540" dealer="0" win="0" bet="35" muck="1" rebuy="0" addon="0" merge="0" rebuychips="0" reg_code="8394365259"/>
<player seat="3" name="oreiasccp" chips="685" dealer="1" win="0" bet="5" muck="1" rebuy="0" addon="0" merge="0" rebuychips="0" reg_code="8394365221"/>
<player seat="6" name="Elbarto212" chips="275" dealer="0" win="75" bet="275" muck="1" rebuy="0" addon="0" merge="0" rebuychips="0" reg_code="8394365250"/>
</players>
</general>
<round no="0"><action no="1" player="Elbarto212" type="15" discard="1" dealt="1" sum="5"/>
<action no="2" player="Freya761" type="15" discard="1" dealt="1" sum="5"/>
<action no="3" player="oreiasccp" type="15" sum="5"/>
<action no="4" player="Elbarto212" type="1" discard="1" dealt="1" sum="15"/>
<action no="5" player="Freya761" type="2" discard="1" dealt="1" sum="30"/>
</round>
<round no="1"><cards type="Pocket" player="Elbarto212">X X</cards>
<cards type="Pocket" player="Freya761">X X</cards>
<cards type="Pocket" player="oreiasccp">DK C8</cards>
<action no="6" player="oreiasccp" type="0" sum="0"/>
<action no="7" player="Elbarto212" type="23" discard="1" dealt="1" sum="270"/>
<action no="8" player="Freya761" type="0" discard="1" dealt="1" sum="0"/>
</round>
</game>
<game gamecode="11540931043"><general><startdate>2025-06-29 14:38:54</startdate>
<round>1</round>
<failsafecounter/>
<players><player seat="3" name="oreiasccp" chips="680" dealer="0" win="45" bet="35" muck="1" rebuy="0" addon="0" merge="0" rebuychips="0" reg_code="8394365221"/>
<player seat="6" name="Elbarto212" chips="315" dealer="1" win="0" bet="5" muck="1" rebuy="0" addon="0" merge="0" rebuychips="0" reg_code="8394365250"/>
<player seat="10" name="Freya761" chips="505" dealer="0" win="0" bet="20" muck="1" rebuy="0" addon="0" merge="0" rebuychips="0" reg_code="8394365259"/>
</players>
</general>
<round no="0"><action no="1" player="Freya761" type="15" discard="1" dealt="1" sum="5"/>
<action no="2" player="oreiasccp" type="15" sum="5"/>
<action no="3" player="Elbarto212" type="15" discard="1" dealt="1" sum="5"/>
<action no="4" player="Freya761" type="1" discard="1" dealt="1" sum="15"/>
<action no="5" player="oreiasccp" type="2" sum="30"/>
</round>
<round no="1"><cards type="Pocket" player="oreiasccp">C3 C10</cards>
<cards type="Pocket" player="Elbarto212">X X</cards>
<cards type="Pocket" player="Freya761">X X</cards>
<action no="6" player="Elbarto212" type="0" discard="1" dealt="1" sum="0"/>
<action no="7" player="Freya761" type="0" discard="1" dealt="1" sum="0"/>
</round>
</game>
<game gamecode="11540931075"><general><startdate>2025-06-29 14:39:02</startdate>
<round>1</round>
<failsafecounter/>
<players><player seat="6" name="Elbarto212" chips="310" dealer="0" win="0" bet="310" muck="0" rebuy="0" addon="0" merge="0" rebuychips="0" reg_code="8394365250"/>
<player seat="10" name="Freya761" chips="485" dealer="1" win="640" bet="310" muck="0" rebuy="0" addon="0" merge="0" rebuychips="0" reg_code="8394365259"/>
<player seat="3" name="oreiasccp" chips="705" dealer="0" win="0" bet="20" muck="1" rebuy="0" addon="0" merge="0" rebuychips="0" reg_code="8394365221"/>
</players>
</general>
<round no="0"><action no="1" player="oreiasccp" type="15" sum="5"/>
<action no="2" player="Elbarto212" type="15" discard="1" dealt="1" sum="5"/>
<action no="3" player="Freya761" type="15" discard="1" dealt="1" sum="5"/>
<action no="4" player="oreiasccp" type="1" sum="15"/>
<action no="5" player="Elbarto212" type="2" discard="1" dealt="1" sum="30"/>
</round>
<round no="1"><cards type="Pocket" player="Freya761">D10 D9</cards>
<cards type="Pocket" player="oreiasccp">S2 DA</cards>
<cards type="Pocket" player="Elbarto212">HA C7</cards>
<action no="6" player="Freya761" type="23" discard="1" dealt="1" sum="60"/>
<action no="7" player="oreiasccp" type="0" sum="0"/>
<action no="8" player="Elbarto212" type="23" discard="1" dealt="1" sum="305"/>
<action no="9" player="Freya761" type="3" discard="1" dealt="1" sum="245"/>
</round>
<round no="2"><cards type="Flop">S4 DQ H9</cards>
</round>
<round no="3"><cards type="Turn">S10</cards>
</round>
<round no="4"><cards type="River">CK</cards>
</round>
</game>
<game gamecode="11540931171"><general><startdate>2025-06-29 14:39:26</startdate>
<round>1</round>
<failsafecounter/>
<players><player seat="10" name="Freya761" chips="815" dealer="0" win="50" bet="45" muck="1" rebuy="0" addon="0" merge="0" rebuychips="0" reg_code="8394365259"/>
<player seat="3" name="oreiasccp" chips="685" dealer="1" win="0" bet="25" muck="1" rebuy="0" addon="0" merge="0" rebuychips="0" reg_code="8394365221"/>
</players>
</general>
<round no="0"><action no="1" player="oreiasccp" type="15" sum="5"/>
<action no="2" player="Freya761" type="15" discard="1" dealt="1" sum="5"/>
<action no="3" player="oreiasccp" type="1" sum="20"/>
<action no="4" player="Freya761" type="2" discard="1" dealt="1" sum="40"/>
</round>
<round no="1"><cards type="Pocket" player="oreiasccp">H8 S2</cards>
<cards type="Pocket" player="Freya761">X X</cards>
<action no="5" player="oreiasccp" type="0" sum="0"/>
</round>
</game>
<game gamecode="11540931192"><general><startdate>2025-06-29 14:39:31</startdate>
<round>1</round>
<failsafecounter/>
<players><player seat="3" name="oreiasccp" chips="660" dealer="0" win="0" bet="45" muck="1" rebuy="0" addon="0" merge="0" rebuychips="0" reg_code="8394365221"/>
<player seat="10" name="Freya761" chips="840" dealer="1" win="90" bet="840" muck="1" rebuy="0" addon="0" merge="0" rebuychips="0" reg_code="8394365259"/>
</players>
</general>
<round no="0"><action no="1" player="Freya761" type="15" discard="1" dealt="1" sum="5"/>
<action no="2" player="oreiasccp" type="15" sum="5"/>
<action no="3" player="Freya761" type="1" discard="1" dealt="1" sum="20"/>
<action no="4" player="oreiasccp" type="2" sum="40"/>
</round>
<round no="1"><cards type="Pocket" player="Freya761">X X</cards>
<cards type="Pocket" player="oreiasccp">HJ S5</cards>
<action no="5" player="Freya761" type="23" discard="1" dealt="1" sum="835"/>
<action no="6" player="oreiasccp" type="0" sum="0"/>
</round>
</game>
<game gamecode="11540931234"><general><startdate>2025-06-29 14:39:40</startdate>
<round>1</round>
<failsafecounter/>
<players><player seat="10" name="Freya761" chips="885" dealer="0" win="0" bet="85" muck="1" rebuy="0" addon="0" merge="0" rebuychips="0" reg_code="8394365259"/>
<player seat="3" name="oreiasccp" chips="615" dealer="1" win="170" bet="125" muck="1" rebuy="0" addon="0" merge="0" rebuychips="0" reg_code="8394365221"/>
</players>
</general>
<round no="0"><action no="1" player="oreiasccp" type="15" sum="5"/>
<action no="2" player="Freya761" type="15" discard="1" dealt="1" sum="5"/>
<action no="3" player="oreiasccp" type="1" sum="20"/>
<action no="4" player="Freya761" type="2" discard="1" dealt="1" sum="40"/>
</round>
<round no="1"><cards type="Pocket" player="Freya761">X X</cards>
<cards type="Pocket" player="oreiasccp">HA SQ</cards>
<action no="5" player="oreiasccp" type="23" sum="80"/>
<action no="6" player="Freya761" type="3" discard="1" dealt="1" sum="40"/>
</round>
<round no="2"><cards type="Flop">H4 H3 H10</cards>
<action no="7" player="Freya761" type="4" discard="1" dealt="1" sum="0"/>
<action no="8" player="oreiasccp" type="5" sum="40"/>
<action no="9" player="Freya761" type="0" discard="1" dealt="1" sum="0"/>
</round>
</game>
<game gamecode="11540931307"><general><startdate>2025-06-29 14:39:54</startdate>
<round>1</round>
<failsafecounter/>
<players><player seat="3" name="oreiasccp" chips="700" dealer="0" win="50" bet="45" muck="1" rebuy="0" addon="0" merge="0" rebuychips="0" reg_code="8394365221"/>
<player seat="10" name="Freya761" chips="800" dealer="1" win="0" bet="25" muck="1" rebuy="0" addon="0" merge="0" rebuychips="0" reg_code="8394365259"/>
</players>
</general>
<round no="0"><action no="1" player="Freya761" type="15" discard="1" dealt="1" sum="5"/>
<action no="2" player="oreiasccp" type="15" sum="5"/>
<action no="3" player="Freya761" type="1" discard="1" dealt="1" sum="20"/>
<action no="4" player="oreiasccp" type="2" sum="40"/>
</round>
<round no="1"><cards type="Pocket" player="Freya761">X X</cards>
<cards type="Pocket" player="oreiasccp">C9 C4</cards>
<action no="5" player="Freya761" type="0" discard="1" dealt="1" sum="0"/>
</round>
</game>
<game gamecode="11540931338"><general><startdate>2025-06-29 14:40:00</startdate>
<round>1</round>
<failsafecounter/>
<players><player seat="10" name="Freya761" chips="775" dealer="0" win="0" bet="775" muck="1" rebuy="0" addon="0" merge="0" rebuychips="0" reg_code="8394365259"/>
<player seat="3" name="oreiasccp" chips="725" dealer="1" win="1,450" bet="725" muck="0" rebuy="0" addon="0" merge="0" rebuychips="0" reg_code="8394365221"/>
</players>
</general>
<round no="0"><action no="1" player="oreiasccp" type="15" sum="5"/>
<action no="2" player="Freya761" type="15" discard="1" dealt="1" sum="5"/>
<action no="3" player="oreiasccp" type="1" sum="20"/>
<action no="4" player="Freya761" type="2" discard="1" dealt="1" sum="40"/>
</round>
<round no="1"><cards type="Pocket" player="oreiasccp">D10 S10</cards>
<cards type="Pocket" player="Freya761">HQ HK</cards>
<action no="5" player="oreiasccp" type="23" sum="80"/>
<action no="6" player="Freya761" type="23" discard="1" dealt="1" sum="770"/>
<action no="7" player="oreiasccp" type="7" sum="640"/>
</round>
<round no="2"><cards type="Flop">D6 D7 C10</cards>
</round>
<round no="3"><cards type="Turn">C9</cards>
</round>
<round no="4"><cards type="River">DA</cards>
</round>
</game>
<game gamecode="11540931449"><general><startdate>2025-06-29 14:40:20</startdate>
<round>1</round>
<failsafecounter/>
<players><player seat="3" name="oreiasccp" chips="1,450" dealer="0" win="100" bet="50" muck="0" rebuy="0" addon="0" merge="0" rebuychips="0" reg_code="8394365221"/>
<player seat="10" name="Freya761" chips="50" dealer="1" win="0" bet="50" muck="0" rebuy="0" addon="0" merge="0" rebuychips="0" reg_code="8394365259"/>
</players>
</general>
<round no="0"><action no="1" player="Freya761" type="15" discard="1" dealt="1" sum="5"/>
<action no="2" player="oreiasccp" type="15" sum="5"/>
<action no="3" player="Freya761" type="1" discard="1" dealt="1" sum="20"/>
<action no="4" player="oreiasccp" type="2" sum="40"/>
</round>
<round no="1"><cards type="Pocket" player="Freya761">CQ HK</cards>
<cards type="Pocket" player="oreiasccp">CA C10</cards>
<action no="5" player="Freya761" type="7" discard="1" dealt="1" sum="25"/>
<action no="6" player="oreiasccp" type="3" sum="5"/>
</round>
<round no="2"><cards type="Flop">HA D10 H6</cards>
</round>
<round no="3"><cards type="Turn">S4</cards>
</round>
<round no="4"><cards type="River">D2</cards>
</round>
</game>
</session>
