<?xml version="1.0" encoding="UTF-8"?>
<session sessioncode="8407814043">
<general>
<client_version>25.1.1.13</client_version>
<mode>real</mode>
<gametype>Holdem NL</gametype>
<tablename>Twister €5 SNG, 1130670990</tablename>
<tournamentcode>1130670989</tournamentcode>
<tournamentname>Twister €5 SNG</tournamentname>
<buyin>€0 + €0.35 + €4.65</buyin>
<totalbuyin>€5</totalbuyin>
<rewarddrawn>€25</rewarddrawn>
<tournamentcurrency>EUR</tournamentcurrency>
<currency>EUR</currency>
<nickname>oreiasccp</nickname>
<gamecount>13</gamecount>
<startdate>2025-07-17 08:47:37</startdate>
<place>3</place>
<win>€0</win>
<tablesize>3</tablesize>
</general>
<game gamecode="11578083705"><general><startdate>2025-07-17 08:47:53</startdate>
<round>1</round>
<failsafecounter/>
<players><player seat="3" name="Laughing4ever" chips="500" dealer="0" win="20" bet="20" muck="1" rebuy="0" addon="0" merge="0" rebuychips="0" reg_code="8407813948"/>
<player seat="6" name="oreiasccp" chips="500" dealer="1" win="0" bet="0" muck="1" rebuy="0" addon="0" merge="0" rebuychips="0" reg_code="8407814043"/>
<player seat="10" name="led291" chips="500" dealer="0" win="0" bet="10" muck="1" rebuy="0" addon="0" merge="0" rebuychips="0" reg_code="8407814076"/>
</players>
</general>
<round no="0"><action no="1" player="led291" type="1" discard="1" dealt="1" sum="10"/>
<action no="2" player="Laughing4ever" type="2" discard="1" dealt="1" sum="20"/>
</round>
<round no="1"><cards type="Pocket" player="oreiasccp">D4 C5</cards>
<cards type="Pocket" player="led291">X X</cards>
<cards type="Pocket" player="Laughing4ever">X X</cards>
<action no="3" player="oreiasccp" type="0" sum="0"/>
<action no="4" player="led291" type="0" discard="1" dealt="1" sum="0"/>
</round>
</game>
<game gamecode="11578083729"><general><startdate>2025-07-17 08:48:03</startdate>
<round>1</round>
<failsafecounter/>
<players><player seat="6" name="oreiasccp" chips="500" dealer="0" win="0" bet="20" muck="1" rebuy="0" addon="0" merge="0" rebuychips="0" reg_code="8407814043"/>
<player seat="10" name="led291" chips="490" dealer="1" win="0" bet="0" muck="1" rebuy="0" addon="0" merge="0" rebuychips="0" reg_code="8407814076"/>
<player seat="3" name="Laughing4ever" chips="510" dealer="0" win="40" bet="60" muck="1" rebuy="0" addon="0" merge="0" rebuychips="0" reg_code="8407813948"/>
</players>
</general>
<round no="0"><action no="1" player="Laughing4ever" type="1" discard="1" dealt="1" sum="10"/>
<action no="2" player="oreiasccp" type="2" sum="20"/>
</round>
<round no="1"><cards type="Pocket" player="oreiasccp">H3 C2</cards>
<cards type="Pocket" player="led291">X X</cards>
<cards type="Pocket" player="Laughing4ever">X X</cards>
<action no="3" player="led291" type="0" discard="1" dealt="1" sum="0"/>
<action no="4" player="Laughing4ever" type="23" discard="1" dealt="1" sum="60"/>
<action no="5" player="oreiasccp" type="0" sum="0"/>
</round>
</game>
<game gamecode="11578083763"><general><startdate>2025-07-17 08:48:15</startdate>
<round>1</round>
<failsafecounter/>
<players><player seat="10" name="led291" chips="490" dealer="0" win="200" bet="100" muck="0" rebuy="0" addon="0" merge="0" rebuychips="0" reg_code="8407814076"/>
<player seat="3" name="Laughing4ever" chips="530" dealer="1" win="0" bet="0" muck="1" rebuy="0" addon="0" merge="0" rebuychips="0" reg_code="8407813948"/>
<player seat="6" name="oreiasccp" chips="480" dealer="0" win="0" bet="100" muck="0" rebuy="0" addon="0" merge="0" rebuychips="0" reg_code="8407814043"/>
</players>
</general>
<round no="0"><action no="1" player="oreiasccp" type="1" sum="10"/>
<action no="2" player="led291" type="2" discard="1" dealt="1" sum="20"/>
</round>
<round no="1"><cards type="Pocket" player="led291">D6 DK</cards>
<cards type="Pocket" player="Laughing4ever">X X</cards>
<cards type="Pocket" player="oreiasccp">HQ H4</cards>
<action no="3" player="Laughing4ever" type="0" discard="1" dealt="1" sum="0"/>
<action no="4" player="oreiasccp" type="23" sum="40"/>
<action no="5" player="led291" type="3" discard="1" dealt="1" sum="20"/>
</round>
<round no="2"><cards type="Flop">H6 SA S4</cards>
<action no="6" player="oreiasccp" type="5" sum="20"/>
<action no="7" player="led291" type="3" discard="1" dealt="1" sum="20"/>
</round>
<round no="3"><cards type="Turn">C10</cards>
<action no="8" player="oreiasccp" type="4" sum="0"/>
<action no="9" player="led291" type="4" discard="1" dealt="1" sum="0"/>
</round>
<round no="4"><cards type="River">DA</cards>
<action no="10" player="oreiasccp" type="5" sum="40"/>
<action no="11" player="led291" type="3" discard="1" dealt="1" sum="40"/>
</round>
</game>
<game gamecode="11578083890"><general><startdate>2025-07-17 08:49:05</startdate>
<round>1</round>
<failsafecounter/>
<players><player seat="3" name="Laughing4ever" chips="530" dealer="0" win="0" bet="20" muck="1" rebuy="0" addon="0" merge="0" rebuychips="0" reg_code="8407813948"/>
<player seat="6" name="oreiasccp" chips="380" dealer="1" win="0" bet="40" muck="1" rebuy="0" addon="0" merge="0" rebuychips="0" reg_code="8407814043"/>
<player seat="10" name="led291" chips="590" dealer="0" win="100" bet="590" muck="1" rebuy="0" addon="0" merge="0" rebuychips="0" reg_code="8407814076"/>
</players>
</general>
<round no="0"><action no="1" player="led291" type="1" discard="1" dealt="1" sum="10"/>
<action no="2" player="Laughing4ever" type="2" discard="1" dealt="1" sum="20"/>
</round>
<round no="1"><cards type="Pocket" player="Laughing4ever">X X</cards>
<cards type="Pocket" player="oreiasccp">SJ HK</cards>
<cards type="Pocket" player="led291">X X</cards>
<action no="3" player="oreiasccp" type="23" sum="40"/>
<action no="4" player="led291" type="23" discard="1" dealt="1" sum="590"/>
<action no="5" player="Laughing4ever" type="0" discard="1" dealt="1" sum="0"/>
<action no="6" player="oreiasccp" type="0" sum="0"/>
</round>
</game>
<game gamecode="11578083923"><general><startdate>2025-07-17 08:49:19</startdate>
<round>1</round>
<failsafecounter/>
<players><player seat="6" name="oreiasccp" chips="340" dealer="0" win="0" bet="20" muck="1" rebuy="0" addon="0" merge="0" rebuychips="0" reg_code="8407814043"/>
<player seat="10" name="led291" chips="650" dealer="1" win="0" bet="0" muck="1" rebuy="0" addon="0" merge="0" rebuychips="0" reg_code="8407814076"/>
<player seat="3" name="Laughing4ever" chips="510" dealer="0" win="40" bet="50" muck="1" rebuy="0" addon="0" merge="0" rebuychips="0" reg_code="8407813948"/>
</players>
</general>
<round no="0"><action no="1" player="Laughing4ever" type="1" discard="1" dealt="1" sum="10"/>
<action no="2" player="oreiasccp" type="2" sum="20"/>
</round>
<round no="1"><cards type="Pocket" player="led291">X X</cards>
<cards type="Pocket" player="Laughing4ever">X X</cards>
<cards type="Pocket" player="oreiasccp">H2 D8</cards>
<action no="3" player="led291" type="0" discard="1" dealt="1" sum="0"/>
<action no="4" player="Laughing4ever" type="23" discard="1" dealt="1" sum="50"/>
<action no="5" player="oreiasccp" type="0" sum="0"/>
</round>
</game>
<game gamecode="11578083971"><general><startdate>2025-07-17 08:49:37</startdate>
<round>1</round>
<failsafecounter/>
<players><player seat="10" name="led291" chips="650" dealer="0" win="90" bet="130" muck="1" rebuy="0" addon="0" merge="0" rebuychips="0" reg_code="8407814076"/>
<player seat="3" name="Laughing4ever" chips="530" dealer="1" win="0" bet="40" muck="1" rebuy="0" addon="0" merge="0" rebuychips="0" reg_code="8407813948"/>
<player seat="6" name="oreiasccp" chips="320" dealer="0" win="0" bet="10" muck="1" rebuy="0" addon="0" merge="0" rebuychips="0" reg_code="8407814043"/>
</players>
</general>
<round no="0"><action no="1" player="oreiasccp" type="1" sum="10"/>
<action no="2" player="led291" type="2" discard="1" dealt="1" sum="20"/>
</round>
<round no="1"><cards type="Pocket" player="Laughing4ever">X X</cards>
<cards type="Pocket" player="oreiasccp">HK H5</cards>
<cards type="Pocket" player="led291">X X</cards>
<action no="3" player="Laughing4ever" type="23" discard="1" dealt="1" sum="40"/>
<action no="4" player="oreiasccp" type="0" sum="0"/>
<action no="5" player="led291" type="3" discard="1" dealt="1" sum="20"/>
</round>
<round no="2"><cards type="Flop">H6 H8 C5</cards>
<action no="6" player="led291" type="4" discard="1" dealt="1" sum="0"/>
<action no="7" player="Laughing4ever" type="4" discard="1" dealt="1" sum="0"/>
</round>
<round no="3"><cards type="Turn">C2</cards>
<action no="8" player="led291" type="4" discard="1" dealt="1" sum="0"/>
<action no="9" player="Laughing4ever" type="4" discard="1" dealt="1" sum="0"/>
</round>
<round no="4"><cards type="River">D4</cards>
<action no="10" player="led291" type="5" discard="1" dealt="1" sum="90"/>
<action no="11" player="Laughing4ever" type="0" discard="1" dealt="1" sum="0"/>
</round>
</game>
<game gamecode="11578084089"><general><startdate>2025-07-17 08:50:27</startdate>
<round>1</round>
<failsafecounter/>
<players><player seat="3" name="Laughing4ever" chips="490" dealer="0" win="0" bet="35" muck="1" rebuy="0" addon="0" merge="0" rebuychips="0" reg_code="8407813948"/>
<player seat="6" name="oreiasccp" chips="310" dealer="1" win="90" bet="310" muck="1" rebuy="0" addon="0" merge="0" rebuychips="0" reg_code="8407814043"/>
<player seat="10" name="led291" chips="700" dealer="0" win="0" bet="20" muck="1" rebuy="0" addon="0" merge="0" rebuychips="0" reg_code="8407814076"/>
</players>
</general>
<round no="0"><action no="1" player="led291" type="15" discard="1" dealt="1" sum="5"/>
<action no="2" player="Laughing4ever" type="15" discard="1" dealt="1" sum="5"/>
<action no="3" player="oreiasccp" type="15" sum="5"/>
<action no="4" player="led291" type="1" discard="1" dealt="1" sum="15"/>
<action no="5" player="Laughing4ever" type="2" discard="1" dealt="1" sum="30"/>
</round>
<round no="1"><cards type="Pocket" player="led291">X X</cards>
<cards type="Pocket" player="oreiasccp">CJ CK</cards>
<cards type="Pocket" player="Laughing4ever">X X</cards>
<action no="6" player="oreiasccp" type="23" sum="305"/>
<action no="7" player="led291" type="0" discard="1" dealt="1" sum="0"/>
<action no="8" player="Laughing4ever" type="0" discard="1" dealt="1" sum="0"/>
</round>
</game>
<game gamecode="11578084129"><general><startdate>2025-07-17 08:50:41</startdate>
<round>1</round>
<failsafecounter/>
<players><player seat="6" name="oreiasccp" chips="365" dealer="0" win="0" bet="65" muck="1" rebuy="0" addon="0" merge="0" rebuychips="0" reg_code="8407814043"/>
<player seat="10" name="led291" chips="680" dealer="1" win="150" bet="95" muck="1" rebuy="0" addon="0" merge="0" rebuychips="0" reg_code="8407814076"/>
<player seat="3" name="Laughing4ever" chips="455" dealer="0" win="0" bet="20" muck="1" rebuy="0" addon="0" merge="0" rebuychips="0" reg_code="8407813948"/>
</players>
</general>
<round no="0"><action no="1" player="Laughing4ever" type="15" discard="1" dealt="1" sum="5"/>
<action no="2" player="oreiasccp" type="15" sum="5"/>
<action no="3" player="led291" type="15" discard="1" dealt="1" sum="5"/>
<action no="4" player="Laughing4ever" type="1" discard="1" dealt="1" sum="15"/>
<action no="5" player="oreiasccp" type="2" sum="30"/>
</round>
<round no="1"><cards type="Pocket" player="oreiasccp">CJ C6</cards>
<cards type="Pocket" player="Laughing4ever">X X</cards>
<cards type="Pocket" player="led291">X X</cards>
<action no="6" player="led291" type="23" discard="1" dealt="1" sum="60"/>
<action no="7" player="Laughing4ever" type="0" discard="1" dealt="1" sum="0"/>
<action no="8" player="oreiasccp" type="3" sum="30"/>
</round>
<round no="2"><cards type="Flop">D8 SA DK</cards>
<action no="9" player="oreiasccp" type="4" sum="0"/>
<action no="10" player="led291" type="5" discard="1" dealt="1" sum="30"/>
<action no="11" player="oreiasccp" type="0" sum="0"/>
</round>
</game>
<game gamecode="11578084207"><general><startdate>2025-07-17 08:51:08</startdate>
<round>1</round>
<failsafecounter/>
<players><player seat="10" name="led291" chips="765" dealer="0" win="0" bet="35" muck="1" rebuy="0" addon="0" merge="0" rebuychips="0" reg_code="8407814076"/>
<player seat="3" name="Laughing4ever" chips="435" dealer="1" win="90" bet="435" muck="1" rebuy="0" addon="0" merge="0" rebuychips="0" reg_code="8407813948"/>
<player seat="6" name="oreiasccp" chips="300" dealer="0" win="0" bet="20" muck="1" rebuy="0" addon="0" merge="0" rebuychips="0" reg_code="8407814043"/>
</players>
</general>
<round no="0"><action no="1" player="oreiasccp" type="15" sum="5"/>
<action no="2" player="led291" type="15" discard="1" dealt="1" sum="5"/>
<action no="3" player="Laughing4ever" type="15" discard="1" dealt="1" sum="5"/>
<action no="4" player="oreiasccp" type="1" sum="15"/>
<action no="5" player="led291" type="2" discard="1" dealt="1" sum="30"/>
</round>
<round no="1"><cards type="Pocket" player="oreiasccp">S3 H2</cards>
<cards type="Pocket" player="led291">X X</cards>
<cards type="Pocket" player="Laughing4ever">X X</cards>
<action no="6" player="Laughing4ever" type="23" discard="1" dealt="1" sum="430"/>
<action no="7" player="oreiasccp" type="0" sum="0"/>
<action no="8" player="led291" type="0" discard="1" dealt="1" sum="0"/>
</round>
</game>
<game gamecode="11578084253"><general><startdate>2025-07-17 08:51:24</startdate>
<round>1</round>
<failsafecounter/>
<players><player seat="3" name="Laughing4ever" chips="490" dealer="0" win="135" bet="490" muck="1" rebuy="0" addon="0" merge="0" rebuychips="0" reg_code="8407813948"/>
<player seat="6" name="oreiasccp" chips="280" dealer="1" win="0" bet="5" muck="1" rebuy="0" addon="0" merge="0" rebuychips="0" reg_code="8407814043"/>
<player seat="10" name="led291" chips="730" dealer="0" win="0" bet="65" muck="1" rebuy="0" addon="0" merge="0" rebuychips="0" reg_code="8407814076"/>
</players>
</general>
<round no="0"><action no="1" player="led291" type="15" discard="1" dealt="1" sum="5"/>
<action no="2" player="Laughing4ever" type="15" discard="1" dealt="1" sum="5"/>
<action no="3" player="oreiasccp" type="15" sum="5"/>
<action no="4" player="led291" type="1" discard="1" dealt="1" sum="15"/>
<action no="5" player="Laughing4ever" type="2" discard="1" dealt="1" sum="30"/>
</round>
<round no="1"><cards type="Pocket" player="led291">X X</cards>
<cards type="Pocket" player="Laughing4ever">X X</cards>
<cards type="Pocket" player="oreiasccp">D4 D6</cards>
<action no="6" player="oreiasccp" type="0" sum="0"/>
<action no="7" player="led291" type="23" discard="1" dealt="1" sum="60"/>
<action no="8" player="Laughing4ever" type="23" discard="1" dealt="1" sum="485"/>
<action no="9" player="led291" type="0" discard="1" dealt="1" sum="0"/>
</round>
</game>
<game gamecode="11578084305"><general><startdate>2025-07-17 08:51:44</startdate>
<round>1</round>
<failsafecounter/>
<players><player seat="6" name="oreiasccp" chips="275" dealer="0" win="0" bet="35" muck="1" rebuy="0" addon="0" merge="0" rebuychips="0" reg_code="8407814043"/>
<player seat="10" name="led291" chips="665" dealer="1" win="0" bet="65" muck="1" rebuy="0" addon="0" merge="0" rebuychips="0" reg_code="8407814076"/>
<player seat="3" name="Laughing4ever" chips="560" dealer="0" win="165" bet="560" muck="1" rebuy="0" addon="0" merge="0" rebuychips="0" reg_code="8407813948"/>
</players>
</general>
<round no="0"><action no="1" player="Laughing4ever" type="15" discard="1" dealt="1" sum="5"/>
<action no="2" player="oreiasccp" type="15" sum="5"/>
<action no="3" player="led291" type="15" discard="1" dealt="1" sum="5"/>
<action no="4" player="Laughing4ever" type="1" discard="1" dealt="1" sum="15"/>
<action no="5" player="oreiasccp" type="2" sum="30"/>
</round>
<round no="1"><cards type="Pocket" player="oreiasccp">S7 S10</cards>
<cards type="Pocket" player="led291">X X</cards>
<cards type="Pocket" player="Laughing4ever">X X</cards>
<action no="6" player="led291" type="23" discard="1" dealt="1" sum="60"/>
<action no="7" player="Laughing4ever" type="23" discard="1" dealt="1" sum="555"/>
<action no="8" player="oreiasccp" type="0" sum="0"/>
<action no="9" player="led291" type="0" discard="1" dealt="1" sum="0"/>
</round>
</game>
<game gamecode="11578084366"><general><startdate>2025-07-17 08:52:03</startdate>
<round>1</round>
<failsafecounter/>
<players><player seat="10" name="led291" chips="600" dealer="0" win="0" bet="45" muck="1" rebuy="0" addon="0" merge="0" rebuychips="0" reg_code="8407814076"/>
<player seat="3" name="Laughing4ever" chips="660" dealer="1" win="0" bet="5" muck="1" rebuy="0" addon="0" merge="0" rebuychips="0" reg_code="8407813948"/>
<player seat="6" name="oreiasccp" chips="240" dealer="0" win="95" bet="240" muck="1" rebuy="0" addon="0" merge="0" rebuychips="0" reg_code="8407814043"/>
</players>
</general>
<round no="0"><action no="1" player="oreiasccp" type="15" sum="5"/>
<action no="2" player="led291" type="15" discard="1" dealt="1" sum="5"/>
<action no="3" player="Laughing4ever" type="15" discard="1" dealt="1" sum="5"/>
<action no="4" player="oreiasccp" type="1" sum="20"/>
<action no="5" player="led291" type="2" discard="1" dealt="1" sum="40"/>
</round>
<round no="1"><cards type="Pocket" player="Laughing4ever">X X</cards>
<cards type="Pocket" player="oreiasccp">S6 SK</cards>
<cards type="Pocket" player="led291">X X</cards>
<action no="6" player="Laughing4ever" type="0" discard="1" dealt="1" sum="0"/>
<action no="7" player="oreiasccp" type="23" sum="235"/>
<action no="8" player="led291" type="0" discard="1" dealt="1" sum="0"/>
</round>
</game>
<game gamecode="11578084399"><general><startdate>2025-07-17 08:52:13</startdate>
<round>1</round>
<failsafecounter/>
<players><player seat="3" name="Laughing4ever" chips="655" dealer="0" win="605" bet="290" muck="0" rebuy="0" addon="0" merge="0" rebuychips="0" reg_code="8407813948"/>
<player seat="6" name="oreiasccp" chips="290" dealer="1" win="0" bet="290" muck="0" rebuy="0" addon="0" merge="0" rebuychips="0" reg_code="8407814043"/>
<player seat="10" name="led291" chips="555" dealer="0" win="0" bet="25" muck="1" rebuy="0" addon="0" merge="0" rebuychips="0" reg_code="8407814076"/>
</players>
</general>
<round no="0"><action no="1" player="led291" type="15" discard="1" dealt="1" sum="5"/>
<action no="2" player="Laughing4ever" type="15" discard="1" dealt="1" sum="5"/>
<action no="3" player="oreiasccp" type="15" sum="5"/>
<action no="4" player="led291" type="1" discard="1" dealt="1" sum="20"/>
<action no="5" player="Laughing4ever" type="2" discard="1" dealt="1" sum="40"/>
</round>
<round no="1"><cards type="Pocket" player="Laughing4ever">CA DJ</cards>
<cards type="Pocket" player="oreiasccp">DK S10</cards>
<cards type="Pocket" player="led291">X X</cards>
<action no="6" player="oreiasccp" type="23" sum="285"/>
<action no="7" player="led291" type="0" discard="1" dealt="1" sum="0"/>
<action no="8" player="Laughing4ever" type="3" discard="1" dealt="1" sum="245"/>
</round>
<round no="2"><cards type="Flop">D9 S8 C4</cards>
</round>
<round no="3"><cards type="Turn">SJ</cards>
</round>
<round no="4"><cards type="River">H5</cards>
</round>
</game>
</session>
